django_podcast_feed-0.0.3.dist-info/DESCRIPTION.rst
django_podcast_feed-0.0.3.dist-info/METADATA
django_podcast_feed-0.0.3.dist-info/RECORD
django_podcast_feed-0.0.3.dist-info/WHEEL
django_podcast_feed-0.0.3.dist-info/metadata.json
django_podcast_feed-0.0.3.dist-info/top_level.txt
podcast_feed/__init__.py
tests/__init__.py
