Metadata-Version: 2.0
Name: django-podcast-feed
Version: 0.0.3
Summary: Generate Apple Podcasts-compatible syndication feeds.
Home-page: https://github.com/jeffbr13/django-podcast-feed
Author: Ben Jeffrey
Author-email: mail@benjeffrey.net
License: MPL 2.0
Keywords: django podcast feed
Platform: UNKNOWN
Classifier: Development Status :: 3 - Alpha
Classifier: Programming Language :: Python :: 3
Classifier: Intended Audience :: Developers
Classifier: License :: OSI Approved :: Mozilla Public License 2.0 (MPL 2.0)
Classifier: Framework :: Django
Requires-Dist: django
